{"title":"Intro","markdown":{"headingText":"Intro","containsRefs":false,"markdown":"> Volgende opgave was de vaardigheidsproefopdracht voor het inhaalexamen van dit vak (OOP) in augustus 2021\n\n\nUltimate Beast Master is een populaire, Amerikaanse, tv-show waarin topatleten een ongelooflijk zware obstakelkoers zo snel mogelijk moeten afleggen. Enkel de sterkste, meest atletische mannen en vrouwen slagen er in om het einde van het parkoers te bereiken. \n\nAls organisator van de tvshow wordt je gevraagd om een systeem te ontwikkelen waarin een parkoers kan gegenereerd worden waarvan ook de moeilijkheidsgraad kan berekend worden.\n\n## Basisklassen\n\nEerst gaan we de nodige toestellen maken om dan later een parkoers van toestellen aan te leggen volgens volgende klasse:\n\n![](bClassDiagram1.png)\n\n### IDodelijk interface\n\nDeze interface is als volgt: \n\n```csharp\ninterface IDodelijk\n{\n    public bool VeiligheidsActief { get; }\n}\n```\n\nToestellen die mogelijk dodelijk zijn, zullen deze interface hebben.\n\n### Toestel-klasse\n\nAlle toestellen die in een parkoers voorkomen zullen van deze klasse overerven.\n\nHet gaat om een abstracte klasse met:\n\n* Een protected instantievariabele ``tekenChar`` dat standaard ``o`` is. Dit teken zal gebruikt worden om het toestel te visualiseren.\n* Methode ``Teken`` die het ``tekenChar`` op de huidige plek in de console schrijft (met ``Write``).\n* Een abstracte methode ``BerekenMoeilijkheidsgraad`` die een ``int`` als resultaat heeft en geen parameters aanvaardt.\n\n\n\n### Trampoline-klasse\n\n* Is een ``Toestel``.\n* Heeft een default constructor:\n  * die de moeilijkheidsgraad van het object op een willekeurige waarde geeft van 1 tot en met 4 (dat vervolgens in ``BerekenMoeilijkheidsgraad`` zal gebruik worden). \n  * het ``tekenChar`` wordt op een ``t`` ingesteld.\n\n### UltraTrampoline-klasse\n\nEen Ultratrampoline is een trampoline die gevaarlijk is. Er is geen mogelijkheid om netten rond het ding te plaatsen, dus deze klasse verdient zeker de term *dodelijk*.\n\nDe klasse:\n\n* Is een ``Trampoline``.\n* Heeft een default constructor die het ``tekenChar`` op ``T`` instelt.\n* Implementeert de ``IDodelijk`` interface en zal altijd ``false`` teruggeven bij ``VeiligheidsActief`` (de beveiligingsinstelling van een Ultratrampoline kan dus nooit anders zijn).\n* De moeilijkheidsgraad van deze klasse is *\"10 + de waarde die in de default constructor van de ``Trampoline``werd berekend\"*.\n\n### Klimmuur-klasse\n\nEen klimmuur wordt gedefinieerd door het aantal handvaten die de muur heeft.\n\nDe klasse:\n\n* Is een ``Toestel``.\n* Heeft een overloaded constructor waarmee het aantal ``klimelementen`` (handvaten) kan ingesteld worden via een meegegeven ``int``. De ``tekenchar`` is een ``m``.\n* De moeilijkheidsgraad is 3 indien er een even aantal ``klimelementen`` zijn, anders is deze 4.\n\n### DeadWall-klasse\n\nDe dodelijk deadwall is een klimmuur waar eventueel veiligheidsnetten onder kunnen geplaatst worden zodat deelnemers die vallen opgevangen kunnen worden.\n\n* Is een ``Klimmuur``.\n* Heeft een default constructor waarmee kan ingesteld worden of de wall met veiligheidsnetten werkt of niet (aan de hand van een meegegeven ``bool``). Een ``DeadWall``heeft altijd ``21`` klimelementen. ``tekenchar`` is ``M``.\n* Implementeert de ``IDodelijke`` interface en zal de ``bool`` teruggeven in ``VeiligheidsActief`` die in de constructor werd meegegeven.\n* De moeilijkheidsgraad is 5 indien er veiligheidsnetten zijn, anders is deze 10.\n\n\n## Parkoer-klasse\n\nDeze klasse beschrijft een volledig parkoers van toestellen die de speler zal moeten bedwingen in de Ultimate Beast Master tv-show.\n\n* Deze klasse heeft een lijst van toestellen.\n* Een constructor die 2 parameters aanvaard, namelijk het aantal toestellen (*x*) waaruit het parkoers bestaat en een bool  (*y*) om aan te geven of dodelijke toestellen met beveiliging moeten worden toegevoegd:\n\t* De constructor zal *x* willekeurige toestellen aan de lijst toevoegen. Ieder toestel (`Trampoline`, `UltraTrampoline`, `Klimmuur` en `Deathwall`) heeft even veel kans om gekozen te worden.\n\t* Indien een `Klimmuur` wordt gekozen dan krijgt deze een willekeurig aantal klimtoppen tussen 10 en 50.\n\t* Indien een Deathwall wordt gekozen dan wordt de bool `y` meegeven om aan te geven of er wel of geen veiligheidsnet moet toegevoegd worden.\n* De klasse heeft een methode `VerwijderDodelijke`. Wanneer deze methode wordt aangeroepen dan worden alle `IDodelijke` toestellen uit de lijst verwijderd.\n* De klasse een private methode `BerekenMoeilijkheidsgraad` die een `int` teruggeeft. De moeilijkheidsgraad van een parkoers bestaat uit de som van de moeilijkheidsgraden van alle toestellen in de lijst.\n* De klasse heeft een methode `ToonParkoers` . Deze methode zal alle toestellen na elkaar op het scherm tonen waarbij de achtergrond van ieder element rood of groen zal zijn:\n\t* Rood indien het een `IDodelijk` toestel is (ongeacht of er veiligheidsnetten aanwezig zijn), groen in de andere gevallen.\n    * Nadien wordt ook nog de totale moeilijkheidsgraad van het parkoers getoond.\n    * Voorbeeld output: ![](outputvb.png)\n\n## Hoofdprogramma\n\nDe hoofdapplicatie bestaat uit volgende stappen\n\n* Eerst worden er 5 willekeurige `Parkoer`-objecten aangemaakt en in een lijst bewaard.\n* Vervolgens worden alle `Parkoer`-objecten in de lijst gevisualiseerd.\n* De gebruiker kiest met welk parkoer hij verder wilt gaan.\n* Er wordt nu aan de gebruiker gevraagd of de dodelijke toestellen uit het parkoers moeten worden gehaald. Indien ja, wordt dit gedaan (alle ``IDodelijke`` objecten worden uit de lijst van het gekozen ``Parkoer`` object gehaald).\n* Finaal wordt het gekozen parkoers nogmaals getoond, al dan niet zonder de dodelijke toestellen.\n\nVoorbeeld output: ![](fulloutput.png)\n\n\n\n::::{.callout-caution collapse=\"true\" title=\"Oplossing\"}\n> Dank aan Wael Orraby.\n\n\n\nKlasses:\n\n```java\n abstract class Toestel\n{\n    protected char tekenChar = 'o';\n    public void Teken()\n    {\n        Console.Write(tekenChar);\n    }\n    public abstract int BerekenMoeilijkheidsgraad();\n}\n\ninternal class Trampoline : Toestel\n{\n    static Random random = new Random();\n    private int moeilijkheidsgraad;\n    public Trampoline()\n    {\n        tekenChar = 't';\n        \n        moeilijkheidsgraad = random.Next(1, 5);\n    }\n    public override int BerekenMoeilijkheidsgraad()=> this.moeilijkheidsgraad;   \n}\n\ninternal class UltraTrampoline : Trampoline, IDodelijk\n{\n    public UltraTrampoline()\n    {\n        tekenChar = 'T';\n    }\n\n    public bool VeiligheidsActief\n    {\n        get\n        {\n            return false;\n        }\n    }\n\n    public override int BerekenMoeilijkheidsgraad()\n    {\n        return base.BerekenMoeilijkheidsgraad() + 10;\n    }\n}\n\ninternal class Klimmuur : Toestel\n{\n    public Klimmuur(int inaantalHandvaten)\n    {\n        tekenChar = 'm';\n        aantalHandvaten = inaantalHandvaten;\n    }\n    private int aantalHandvaten;\n    public override int BerekenMoeilijkheidsgraad()\n    {\n        if (aantalHandvaten % 2 == 0)\n            return 3;\n        return 4;\n    }\n}\n\ninternal class DeadWall : Klimmuur, IDodelijk\n{\n    private bool veiligheidsNetten;\n\n    public bool VeiligheidsActief\n    {\n        get\n        {\n            return veiligheidsNetten;\n        }\n    }\n\n    public DeadWall(bool heeftVeiligheidsnetten) : base(21)\n    {\n        veiligheidsNetten = heeftVeiligheidsnetten;\n        tekenChar = 'M';\n    }\n    public override int BerekenMoeilijkheidsgraad()\n    {\n        if (VeiligheidsActief) return 5;\n        return 10;\n    }\n}\n\ninternal class Parkoer\n{\n    static Random r = new Random();\n    List<Toestel> toestellenLijst = new List<Toestel>();\n    public Parkoer(int x, bool y)\n    {\n        for (int i = 0; i < x; i++)\n        {\n            int rng = r.Next(1, 5);\n            switch (rng)\n            {\n                case 1:\n                    toestellenLijst.Add(new Trampoline());\n                    break;\n                case 2:\n                    toestellenLijst.Add(new UltraTrampoline());\n                    break;\n                case 3:\n                    toestellenLijst.Add(new Klimmuur(r.Next(10, 51)));\n                    break;\n                case 4:\n                    toestellenLijst.Add(new DeadWall(y));\n                    break;\n            }\n        }\n    }\n    public void VerwijderDodelijke()\n    {\n        var tempLijst = new List<Toestel>();\n        foreach (var item in toestellenLijst)\n        {\n            if (!(item is IDodelijk))\n            {\n                tempLijst.Add(item);\n            }\n        }\n        toestellenLijst = tempLijst;\n    }\n    private int BerekenMoeilijkheidsgraad()\n    {\n        int som = 0;\n        foreach (var item in toestellenLijst)\n        {\n            som += item.BerekenMoeilijkheidsgraad();\n        }\n        return som;\n    }\n    public void ToonParkoers()\n    {\n        foreach (var item in toestellenLijst)\n        {\n            if (item is IDodelijk)\n                Console.BackgroundColor = ConsoleColor.Red;\n            else\n                Console.BackgroundColor = ConsoleColor.Green;\n            Console.ForegroundColor = ConsoleColor.Black;\n            item.Teken();\n            Console.ResetColor();\n        }\n        Console.WriteLine($\"\\nMoeilijkheidsgraad = {BerekenMoeilijkheidsgraad()}\");\n    }\n}\n```\n\nProgram.cs\n\n```java\nList<Parkoer> parkoersList = new List<Parkoer>();\nRandom r = new Random();\nConsole.WriteLine(\"5 Parkoers gemaakt. Met welke wil je verder?\");\nfor (int i = 0; i < 5; i++)\n{\n    parkoersList.Add(new Parkoer(10, r.Next() / 2 == 0 ? true : false));\n}\nfor (int i = 0; i < parkoersList.Count; i++)\n{\n    Console.WriteLine($\"Parkoer {i + 1}\");\n    parkoersList[i].ToonParkoers();\n    Console.WriteLine();\n}\nConsole.WriteLine(\"Typ het nummer in van het parkoer waar je verder mee wenst te gaan:\");\nint parkoerKeuze = int.Parse(Console.ReadLine());\nConsole.WriteLine(\"Wil je in dit parkoer de dodelijke elementen verwijderen ? (j/n)\");\nstring verwijderKeuze = Console.ReadLine();\nif (verwijderKeuze.ToLower() == \"j\")\n{\n    parkoersList[parkoerKeuze - 1].VerwijderDodelijke();\n    Console.WriteLine(\"Verwijderd. Dit is het nieuwe parkoers : \");\n}\nelse\n{\n    Console.WriteLine(\"Oke. Dit is het parkoers : \");\n    \n}\nparkoersList[parkoerKeuze - 1].ToonParkoers();\n```\n::::\n","srcMarkdownNoYaml":""},"formats":{"html":{"identifier":{"display-name":"HTML","target-format":"html","base-format":"html"},"execute":{"fig-width":7,"fig-height":5,"fig-format":"retina","fig-dpi":96,"df-print":"default","error":false,"eval":true,"cache":null,"freeze":false,"echo":true,"output":true,"warning":true,"include":true,"keep-md":false,"keep-ipynb":false,"ipynb":null,"enabled":null,"daemon":null,"daemon-restart":false,"debug":false,"ipynb-filters":[],"ipynb-shell-interactivity":null,"plotly-connected":true,"engine":"markdown"},"render":{"keep-tex":false,"keep-typ":false,"keep-source":false,"keep-hidden":false,"prefer-html":false,"output-divs":true,"output-ext":"html","fig-align":"default","fig-pos":null,"fig-env":null,"code-fold":"none","code-overflow":"scroll","code-link":false,"code-line-numbers":false,"code-tools":false,"tbl-colwidths":"auto","merge-includes":true,"inline-includes":false,"preserve-yaml":false,"latex-auto-mk":true,"latex-auto-install":true,"latex-clean":true,"latex-min-runs":1,"latex-max-runs":10,"latex-makeindex":"makeindex","latex-makeindex-opts":[],"latex-tlmgr-opts":[],"latex-input-paths":[],"latex-output-dir":null,"link-external-icon":false,"link-external-newwindow":false,"self-contained-math":false,"format-resources":[],"notebook-links":true},"pandoc":{"standalone":true,"wrap":"none","default-image-extension":"png","to":"html","toc":true,"output-file":"Opgave_2122.html"},"language":{"toc-title-document":"Inhoudsopgave","toc-title-website":"Op deze pagina","related-formats-title":"Andere formaten","related-notebooks-title":"Notebooks","source-notebooks-prefix":"Bron","other-links-title":"Andere Links","code-links-title":"Code Links","launch-dev-container-title":"Dev Container starten","launch-binder-title":"Binder starten","article-notebook-label":"Artikel Notebook","notebook-preview-download":"Download Notebook","notebook-preview-download-src":"Broncode downloaden","notebook-preview-back":"Terug naar Artikel","manuscript-meca-bundle":"MECA Archief","section-title-abstract":"Samenvatting","section-title-appendices":"Bijlagen","section-title-footnotes":"Voetnoten","section-title-references":"Referenties","section-title-reuse":"Hergebruik","section-title-copyright":"Auteursrechten","section-title-citation":"Citaat","appendix-attribution-cite-as":"Citeer dit werk als:","appendix-attribution-bibtex":"BibTeX citaat:","appendix-view-license":"Licentie Bekijken","title-block-author-single":"Auteur","title-block-author-plural":"Auteurs","title-block-affiliation-single":"Affiliatie","title-block-affiliation-plural":"Affiliaties","title-block-published":"Publicatiedatum","title-block-modified":"Gewijzigd","title-block-keywords":"Trefwoorden","callout-tip-title":"Tip","callout-note-title":"Opmerking","callout-warning-title":"Waarschuwing","callout-important-title":"Belangrijk","callout-caution-title":"Opgelet","code-summary":"Code","code-tools-menu-caption":"Code","code-tools-show-all-code":"Alle code tonen","code-tools-hide-all-code":"Alle code verbergen","code-tools-view-source":"Broncode bekijken","code-tools-source-code":"Broncode","tools-share":"Share","tools-download":"Download","code-line":"Regel","code-lines":"Regels","copy-button-tooltip":"Kopieer naar klembord","copy-button-tooltip-success":"Gekopieerd!","repo-action-links-edit":"Pagina bewerken","repo-action-links-source":"Broncode bekijken","repo-action-links-issue":"Een probleem melden","back-to-top":"Terug naar boven","search-no-results-text":"Geen resultaten","search-matching-documents-text":"Gevonden documenten","search-copy-link-title":"Kopieer link om te zoeken","search-hide-matches-text":"Extra overeenkomsten verbergen","search-more-match-text":"meer overeenkomst in dit document","search-more-matches-text":"meer overeenkomsten in dit document","search-clear-button-title":"Wissen","search-text-placeholder":"","search-detached-cancel-button-title":"Annuleren","search-submit-button-title":"Verzenden","search-label":"Zoeken","toggle-section":"Schakel sectie","toggle-sidebar":"Schakel zijbalknavigatie","toggle-dark-mode":"Schakel donkere modus","toggle-reader-mode":"Schakel leesmodus","toggle-navigation":"Schakel navigatie","crossref-fig-title":"Figuur","crossref-tbl-title":"Tabel","crossref-lst-title":"Listing","crossref-thm-title":"Stelling","crossref-lem-title":"Lemma","crossref-cor-title":"Conclusie","crossref-prp-title":"Voorstel","crossref-cnj-title":"Aanname","crossref-def-title":"Definitie","crossref-exm-title":"Voorbeeld","crossref-exr-title":"Oefening","crossref-ch-prefix":"Hoofdstuk","crossref-apx-prefix":"Bijlage","crossref-sec-prefix":"Paragraaf","crossref-eq-prefix":"Vergelijking","crossref-lof-title":"Lijst van figuren","crossref-lot-title":"Lijst van tabellen","crossref-lol-title":"Lijst van listings","environment-proof-title":"Bewijs","environment-remark-title":"Opmerking","environment-solution-title":"Oplossing","listing-page-order-by":"Sorteer op","listing-page-order-by-default":"Standaard","listing-page-order-by-date-asc":"Oudste","listing-page-order-by-date-desc":"Nieuwste","listing-page-order-by-number-desc":"Aflopend","listing-page-order-by-number-asc":"Oplopend","listing-page-field-date":"Datum","listing-page-field-title":"Titel","listing-page-field-description":"Beschrijving","listing-page-field-author":"Auteur","listing-page-field-filename":"Bestandsnaam","listing-page-field-filemodified":"Gewijzigd","listing-page-field-subtitle":"Subtitel","listing-page-field-readingtime":"Leestijd","listing-page-field-wordcount":"Woordentelling","listing-page-field-categories":"Categorieën","listing-page-minutes-compact":"{0} min","listing-page-category-all":"Alle","listing-page-no-matches":"Geen overeenkomsten","listing-page-words":"{0} woorden","listing-page-filter":"Filter","draft":"Ontwerp"},"metadata":{"lang":"nl","fig-responsive":true,"quarto-version":"1.9.35","engines":[{"path":"C:\\Users\\p008465\\AppData\\Local\\Programs\\Quarto\\share\\extension-subtrees\\julia-engine\\_extensions\\julia-engine\\julia-engine.js"}],"theme":"sandstone"},"extensions":{"book":{"multiFile":true}}}},"projectFormats":["html"]}